{
    "alerts": [],
    "settings": {
        "interface": "emergency",
        "singleViewUid": "261"
    },
    "args": {
        "action": "result",
        "controller": "Search",
        "search": {
            "date": "2025-07-10",
            "lat": "",
            "lng": "",
            "plzort": "Saarland",
            "radius": "25",
            "street": ""
        },
        "token": "216823d96ea25c051509d935955c130fbc72680fc1d3040fe3e8ca0e25f9cd02"
    },
    "results": {
        "parameter": {
            "plzort": "Saarland",
            "strasse": [],
            "radius": "25.0",
            "longitude": "6.9537369",
            "latitude": "49.3841872",
            "limit": [],
            "datum": "10.07.2025"
        },
        "statistik": {
            "anzahl": 13
        },
        "quota": {
            "verwendet": "53315"
        },
        "apotheken": {
            "apotheke": [
                {
                    "name": "Brunnen-Apotheke OHG",
                    "kammer": "aksaar",
                    "id": "1406",
                    "apo_id": "aksaar1406",
                    "strasse": "Am Bahnhof 8",
                    "plz": "66265",
                    "ort": "Heusweiler",
                    "distanz": "5.71660023561",
                    "longitude": "6.928617",
                    "latitude": "49.3354757",
                    "telefon": "06806/6111",
                    "fax": "06806/77134",
                    "email": "Brunnenapotheke-Heusweiler@web.de",
                    "startdatum": "10.07.2025",
                    "startzeit": "08:00",
                    "enddatum": "11.07.2025",
                    "endzeit": "08:00"
                },
                {
                    "name": "Rosen-Apotheke",
                    "kammer": "aksaar",
                    "id": "1853",
                    "apo_id": "aksaar1853",
                    "strasse": "Trierer Straße 11",
                    "plz": "66839",
                    "ort": "Schmelz",
                    "distanz": "9.759805352179999",
                    "longitude": "6.85297",
                    "latitude": "49.44231",
                    "telefon": "06887/92777",
                    "fax": "06887/92779",
                    "email": "info@rosenapotheke.biz",
                    "startdatum": "10.07.2025",
                    "startzeit": "08:00",
                    "enddatum": "11.07.2025",
                    "endzeit": "08:00"
                },
                {
                    "name": "Apotheke am Alten Markt",
                    "kammer": "aksaar",
                    "id": "1237",
                    "apo_id": "aksaar1237",
                    "strasse": "Alter Markt 3",
                    "plz": "66287",
                    "ort": "Quierschied",
                    "distanz": "9.79518500438",
                    "longitude": "7.05337",
                    "latitude": "49.32485",
                    "telefon": "06897/63030",
                    "fax": "06897/66458",
                    "email": "mail@apotheke-am-alten-markt.com",
                    "startdatum": "10.07.2025",
                    "startzeit": "08:00",
                    "enddatum": "11.07.2025",
                    "endzeit": "08:00"
                },
                {
                    "name": "Rosen-Apotheke",
                    "kammer": "aksaar",
                    "id": "1844",
                    "apo_id": "aksaar1844",
                    "strasse": "Im Brühl 1a",
                    "plz": "66646",
                    "ort": "Marpingen-Urexweiler",
                    "distanz": "10.28023173205",
                    "longitude": "7.0768838",
                    "latitude": "49.4298659",
                    "telefon": "06827/2233",
                    "fax": "06827/3289",
                    "email": "team@apotheke-urexweiler.de",
                    "startdatum": "10.07.2025",
                    "startzeit": "08:00",
                    "enddatum": "11.07.2025",
                    "endzeit": "08:00"
                },
                {
                    "name": "Glückauf-Apotheke",
                    "kammer": "aksaar",
                    "id": "1500",
                    "apo_id": "aksaar1500",
                    "strasse": "Bahnhofstr. 14",
                    "plz": "66740",
                    "ort": "Saarlouis-Fraulautern",
                    "distanz": "15.45419755719",
                    "longitude": "6.7611924",
                    "latitude": "49.325121",
                    "telefon": "06831/80560",
                    "fax": "06831/88299",
                    "email": "glueckaufapo@t-online.de",
                    "startdatum": "10.07.2025",
                    "startzeit": "08:00",
                    "enddatum": "11.07.2025",
                    "endzeit": "08:00"
                },
                {
                    "name": "Saarpark-Apotheke",
                    "kammer": "aksaar",
                    "id": "1893",
                    "apo_id": "aksaar1893",
                    "strasse": "Stummplatz 1",
                    "plz": "66538",
                    "ort": "Neunkirchen",
                    "distanz": "16.44807999591",
                    "longitude": "7.1731178",
                    "latitude": "49.347522",
                    "telefon": "06821/1525",
                    "fax": "06821/21245",
                    "email": "saarparkapotheke@t-online.de",
                    "startdatum": "10.07.2025",
                    "startzeit": "08:00",
                    "enddatum": "11.07.2025",
                    "endzeit": "08:00"
                },
                {
                    "name": "easy-Apotheke",
                    "kammer": "aksaar",
                    "id": "1449",
                    "apo_id": "aksaar1449",
                    "strasse": "Jahnstraße 17",
                    "plz": "66763",
                    "ort": "Dillingen",
                    "distanz": "17.007783553320003",
                    "longitude": "6.7234186",
                    "latitude": "49.3565381",
                    "telefon": "06831/4614658",
                    "fax": "06831/4614659",
                    "email": "dillingen@easyapotheken.de",
                    "startdatum": "10.07.2025",
                    "startzeit": "08:00",
                    "enddatum": "11.07.2025",
                    "endzeit": "08:00"
                },
                {
                    "name": "Apotheke am Zoo",
                    "kammer": "aksaar",
                    "id": "1278",
                    "apo_id": "aksaar1278",
                    "strasse": "Brandenburger Platz 12",
                    "plz": "66121",
                    "ort": "Saarbrücken",
                    "distanz": "18.02534246943",
                    "longitude": "7.04286",
                    "latitude": "49.23295",
                    "telefon": "0681/818961",
                    "fax": "0681/818962",
                    "email": "info@apotheke-am-zoo-sb.de",
                    "startdatum": "10.07.2025",
                    "startzeit": "08:00",
                    "enddatum": "11.07.2025",
                    "endzeit": "08:00"
                },
                {
                    "name": "Linden-Apotheke",
                    "kammer": "aksaar",
                    "id": "1628",
                    "apo_id": "aksaar1628",
                    "strasse": "Völklinger Str. 11",
                    "plz": "66333",
                    "ort": "Völklingen-Ludweiler",
                    "distanz": "20.559450269320003",
                    "longitude": "6.8121967",
                    "latitude": "49.2241644",
                    "telefon": "06898/42300",
                    "fax": "06898/43651",
                    "email": "B.Madsen@t-online.de",
                    "startdatum": "10.07.2025",
                    "startzeit": "08:00",
                    "enddatum": "11.07.2025",
                    "endzeit": "08:00"
                },
                {
                    "name": "Florian-Apotheke",
                    "kammer": "aksaar",
                    "id": "1473",
                    "apo_id": "aksaar1473",
                    "strasse": "Hauptstr. 119",
                    "plz": "66386",
                    "ort": "St. Ingbert-Oberwürzbach",
                    "distanz": "20.90792060617",
                    "longitude": "7.1426428",
                    "latitude": "49.2424535",
                    "telefon": "06894/966322",
                    "fax": "06894/966323",
                    "email": "info@florian-apotheke.com",
                    "startdatum": "10.07.2025",
                    "startzeit": "08:00",
                    "enddatum": "11.07.2025",
                    "endzeit": "08:00"
                },
                {
                    "name": "Fellenberg-Apotheke",
                    "kammer": "aksaar",
                    "id": "1470",
                    "apo_id": "aksaar1470",
                    "strasse": "Torstraße 28",
                    "plz": "66663",
                    "ort": "Merzig",
                    "distanz": "23.2561066831",
                    "longitude": "6.6467059",
                    "latitude": "49.4441586",
                    "telefon": "06861/793232",
                    "fax": "06861/793233",
                    "email": "fellenberg-apotheke@t-online.de",
                    "startdatum": "10.07.2025",
                    "startzeit": "08:00",
                    "enddatum": "11.07.2025",
                    "endzeit": "08:00"
                },
                {
                    "name": "Saar-Apotheke",
                    "kammer": "aksaar",
                    "id": "1881",
                    "apo_id": "aksaar1881",
                    "strasse": "Elsässer Straße 1",
                    "plz": "66271",
                    "ort": "Kleinblittersdorf",
                    "distanz": "25.9103911292",
                    "longitude": "7.03447",
                    "latitude": "49.15728",
                    "telefon": "06805/9112-0",
                    "fax": "06805/911222",
                    "email": "info@saar-apotheken.de",
                    "startdatum": "10.07.2025",
                    "startzeit": "08:00",
                    "enddatum": "11.07.2025",
                    "endzeit": "08:00"
                },
                {
                    "name": "Ostertal-Apotheke",
                    "kammer": "aksaar",
                    "id": "1762",
                    "apo_id": "aksaar1762",
                    "strasse": "Talbrückstraße 1",
                    "plz": "66629",
                    "ort": "Freisen-Oberkirchen",
                    "distanz": "27.32179340341",
                    "longitude": "7.2621537",
                    "latitude": "49.5253414",
                    "telefon": "06855/237",
                    "fax": "06855/996650",
                    "email": "info@ostertal-apo-freisen.de",
                    "startdatum": "10.07.2025",
                    "startzeit": "08:00",
                    "enddatum": "11.07.2025",
                    "endzeit": "08:00"
                }
            ]
        }
    }
}