{
    "alerts": [],
    "settings": {
        "interface": "emergency",
        "singleViewUid": "261"
    },
    "args": {
        "action": "result",
        "controller": "Search",
        "search": {
            "date": "",
            "lat": "",
            "lng": "",
            "plzort": "Baden-Württemberg",
            "radius": "25",
            "street": ""
        },
        "token": "216823d96ea25c051509d935955c130fbc72680fc1d3040fe3e8ca0e25f9cd02"
    },
    "results": {
        "parameter": {
            "plzort": "Baden-Württemberg",
            "strasse": [],
            "radius": "25.0",
            "longitude": "9.041169",
            "latitude": "48.537749999999996",
            "limit": [],
            "datum": []
        },
        "statistik": {
            "anzahl": 11
        },
        "quota": {
            "verwendet": "94293"
        },
        "apotheken": {
            "apotheke": [
                {
                    "name": "Post-Apotheke Tübingen",
                    "kammer": "lakbw",
                    "id": "1672015",
                    "apo_id": "lakbw1672015",
                    "strasse": "Europaplatz 3",
                    "plz": "72072",
                    "ort": "Tübingen",
                    "distanz": "2.69959424062",
                    "longitude": "9.0583954",
                    "latitude": "48.5163388",
                    "telefon": "+49 7071 32777",
                    "fax": "+49 7071 34987",
                    "email": [],
                    "startdatum": "23.06.2025",
                    "startzeit": "08:30",
                    "enddatum": "24.06.2025",
                    "endzeit": "08:30"
                },
                {
                    "name": "Rathaus-Apotheke Kirchentellinsfurt",
                    "kammer": "lakbw",
                    "id": "1339001",
                    "apo_id": "lakbw1339001",
                    "strasse": "Dorfstr. 41",
                    "plz": "72138",
                    "ort": "Kirchentellinsfurt",
                    "distanz": "7.91849291125",
                    "longitude": "9.1480319",
                    "latitude": "48.5319196",
                    "telefon": "+49 7121 96880",
                    "fax": "+49 7121 968830",
                    "email": [],
                    "startdatum": "23.06.2025",
                    "startzeit": "08:30",
                    "enddatum": "24.06.2025",
                    "endzeit": "08:30"
                },
                {
                    "name": "Apotheke Ohmenhausen",
                    "kammer": "lakbw",
                    "id": "1553003",
                    "apo_id": "lakbw1553003",
                    "strasse": "Gomaringer Str. 33",
                    "plz": "72770",
                    "ort": "Reutlingen",
                    "distanz": "9.84143085789",
                    "longitude": "9.1367",
                    "latitude": "48.4760818",
                    "telefon": "+49 7121 91660",
                    "fax": "+49 7121 916616",
                    "email": [],
                    "startdatum": "23.06.2025",
                    "startzeit": "08:30",
                    "enddatum": "24.06.2025",
                    "endzeit": "08:30"
                },
                {
                    "name": "Central-Apotheke Schönaich",
                    "kammer": "lakbw",
                    "id": "1628002",
                    "apo_id": "lakbw1628002",
                    "strasse": "Wettgasse 45",
                    "plz": "71101",
                    "ort": "Schönaich",
                    "distanz": "13.247878145709999",
                    "longitude": "9.0598771",
                    "latitude": "48.6562355",
                    "telefon": "+49 7031 651388",
                    "fax": "+49 7031 651387",
                    "email": [],
                    "startdatum": "23.06.2025",
                    "startzeit": "08:30",
                    "enddatum": "24.06.2025",
                    "endzeit": "08:30"
                },
                {
                    "name": "Bären Apotheke Herrenberg",
                    "kammer": "lakbw",
                    "id": "1284009",
                    "apo_id": "lakbw1284009",
                    "strasse": "Hindenburgstr. 20",
                    "plz": "71083",
                    "ort": "Herrenberg",
                    "distanz": "14.157669580870001",
                    "longitude": "8.8695929",
                    "latitude": "48.594684",
                    "telefon": "+49 7032 122110",
                    "fax": "+49 7032 1221120",
                    "email": [],
                    "startdatum": "23.06.2025",
                    "startzeit": "08:30",
                    "enddatum": "24.06.2025",
                    "endzeit": "08:30"
                },
                {
                    "name": "Eichenberg-Apotheke Hirrlingen",
                    "kammer": "lakbw",
                    "id": "1288002",
                    "apo_id": "lakbw1288002",
                    "strasse": "Marktstr. 5",
                    "plz": "72145",
                    "ort": "Hirrlingen",
                    "distanz": "18.14752612762",
                    "longitude": "8.88757",
                    "latitude": "48.41046",
                    "telefon": "+49 7478 91170",
                    "fax": "+49 7478 91172",
                    "email": [],
                    "startdatum": "23.06.2025",
                    "startzeit": "08:30",
                    "enddatum": "24.06.2025",
                    "endzeit": "08:30"
                },
                {
                    "name": "Bahnhof-Apotheke Metzingen",
                    "kammer": "lakbw",
                    "id": "1428002",
                    "apo_id": "lakbw1428002",
                    "strasse": "Schönbeinstr. 20",
                    "plz": "72555",
                    "ort": "Metzingen",
                    "distanz": "18.2614364339",
                    "longitude": "9.2884493",
                    "latitude": "48.5394308",
                    "telefon": "+49 7123 14252",
                    "fax": "+49 7123 41932",
                    "email": [],
                    "startdatum": "23.06.2025",
                    "startzeit": "08:30",
                    "enddatum": "24.06.2025",
                    "endzeit": "08:30"
                },
                {
                    "name": "Rotbühl-Apotheke Sindelfingen",
                    "kammer": "lakbw",
                    "id": "1588012",
                    "apo_id": "lakbw1588012",
                    "strasse": "Leonberger Str. 29",
                    "plz": "71063",
                    "ort": "Sindelfingen",
                    "distanz": "20.05370022793",
                    "longitude": "9.002642",
                    "latitude": "48.7162673",
                    "telefon": "+49 7031 70820",
                    "fax": "+49 7031 708270",
                    "email": [],
                    "startdatum": "23.06.2025",
                    "startzeit": "08:30",
                    "enddatum": "24.06.2025",
                    "endzeit": "08:30"
                },
                {
                    "name": "Apotheke in der SchwabenGalerie",
                    "kammer": "lakbw",
                    "id": "1819025",
                    "apo_id": "lakbw1819025",
                    "strasse": "Schwabenplatz 1",
                    "plz": "70563",
                    "ort": "Stuttgart",
                    "distanz": "21.97031432178",
                    "longitude": "9.1089",
                    "latitude": "48.7301521",
                    "telefon": "+49 711 9976900",
                    "fax": "+49 711 99769022",
                    "email": [],
                    "startdatum": "23.06.2025",
                    "startzeit": "08:30",
                    "enddatum": "24.06.2025",
                    "endzeit": "08:30"
                },
                {
                    "name": "Kronen-Apotheke Neuhausen",
                    "kammer": "lakbw",
                    "id": "1472004",
                    "apo_id": "lakbw1472004",
                    "strasse": "Marktstr. 3",
                    "plz": "73765",
                    "ort": "Neuhausen auf den Fildern",
                    "distanz": "23.99745158336",
                    "longitude": "9.27955",
                    "latitude": "48.68466",
                    "telefon": "+49 7158 67000",
                    "fax": "+49 7158 67111",
                    "email": [],
                    "startdatum": "23.06.2025",
                    "startzeit": "08:30",
                    "enddatum": "24.06.2025",
                    "endzeit": "08:30"
                },
                {
                    "name": "Uhland-Apotheke Nürtingen",
                    "kammer": "lakbw",
                    "id": "1486012",
                    "apo_id": "lakbw1486012",
                    "strasse": "Uhlandstr. 3",
                    "plz": "72622",
                    "ort": "Nürtingen",
                    "distanz": "24.197034426160002",
                    "longitude": "9.3402263",
                    "latitude": "48.6270619",
                    "telefon": "+49 7022 8633",
                    "fax": "+49 7022 33936",
                    "email": [],
                    "startdatum": "23.06.2025",
                    "startzeit": "08:30",
                    "enddatum": "24.06.2025",
                    "endzeit": "08:30"
                }
            ]
        }
    }
}