{
    "alerts": [],
    "settings": {
        "interface": "emergency",
        "singleViewUid": "261"
    },
    "args": {
        "action": "result",
        "controller": "Search",
        "search": {
            "date": "2025-07-09",
            "lat": "",
            "lng": "",
            "plzort": "Sachsen-Anhalt",
            "radius": "25",
            "street": ""
        },
        "token": "216823d96ea25c051509d935955c130fbc72680fc1d3040fe3e8ca0e25f9cd02"
    },
    "results": {
        "parameter": {
            "plzort": "Sachsen-Anhalt",
            "strasse": [],
            "radius": "25.0",
            "longitude": "11.7003344",
            "latitude": "52.008906499999995",
            "limit": [],
            "datum": "09.07.2025"
        },
        "statistik": {
            "anzahl": 7
        },
        "quota": {
            "verwendet": "169429"
        },
        "apotheken": {
            "apotheke": [
                {
                    "name": "Dr. Löwe-Apotheke",
                    "kammer": "aksa",
                    "id": "105",
                    "apo_id": "aksa105",
                    "strasse": "Magdeburger Str. 105",
                    "plz": "39240",
                    "ort": "Calbe/Saale",
                    "distanz": "12.50322668883",
                    "longitude": "11.7717242",
                    "latitude": "51.9055525",
                    "telefon": "+49 39291 2860",
                    "fax": [],
                    "email": [],
                    "startdatum": "09.07.2025",
                    "startzeit": "08:00",
                    "enddatum": "10.07.2025",
                    "endzeit": "08:00"
                },
                {
                    "name": "Germania-Apotheke",
                    "kammer": "aksa",
                    "id": "117",
                    "apo_id": "aksa117",
                    "strasse": "Magdeburg-Leipziger Str.13",
                    "plz": "39443",
                    "ort": "Staßfurt",
                    "distanz": "12.97016758112",
                    "longitude": "11.63172",
                    "latitude": "51.9003204",
                    "telefon": "+49 39266 210",
                    "fax": [],
                    "email": [],
                    "startdatum": "09.07.2025",
                    "startzeit": "08:00",
                    "enddatum": "10.07.2025",
                    "endzeit": "08:00"
                },
                {
                    "name": "Rats-Apotheke im Ulrichshaus",
                    "kammer": "aksa",
                    "id": "54",
                    "apo_id": "aksa54",
                    "strasse": "Ulrichplatz 2",
                    "plz": "39104",
                    "ort": "Magdeburg",
                    "distanz": "14.217934864650001",
                    "longitude": "11.6345988",
                    "latitude": "52.130095",
                    "telefon": "+49 391 5975844",
                    "fax": [],
                    "email": [],
                    "startdatum": "09.07.2025",
                    "startzeit": "08:00",
                    "enddatum": "10.07.2025",
                    "endzeit": "08:00"
                },
                {
                    "name": "Hubertus-Apotheke",
                    "kammer": "aksa",
                    "id": "4",
                    "apo_id": "aksa4",
                    "strasse": "Karl-Marx-Str. 26",
                    "plz": "39175",
                    "ort": "Biederitz",
                    "distanz": "16.98358655966",
                    "longitude": "11.7227316",
                    "latitude": "52.160917",
                    "telefon": "+49 39292 2072",
                    "fax": [],
                    "email": [],
                    "startdatum": "09.07.2025",
                    "startzeit": "08:00",
                    "enddatum": "10.07.2025",
                    "endzeit": "08:00"
                },
                {
                    "name": "Ginkgo-Apotheke OHG",
                    "kammer": "aksa",
                    "id": "657",
                    "apo_id": "aksa657",
                    "strasse": "Johannes-R.-Becher-Str. 42",
                    "plz": "39128",
                    "ort": "Magdeburg",
                    "distanz": "18.39797487311",
                    "longitude": "11.6242338",
                    "latitude": "52.1674686",
                    "telefon": "+49 391 2899877",
                    "fax": [],
                    "email": [],
                    "startdatum": "09.07.2025",
                    "startzeit": "08:00",
                    "enddatum": "10.07.2025",
                    "endzeit": "08:00"
                },
                {
                    "name": "Adler-Apotheke",
                    "kammer": "aksa",
                    "id": "116",
                    "apo_id": "aksa116",
                    "strasse": "Ritterstr. 14",
                    "plz": "39435",
                    "ort": "Egeln",
                    "distanz": "19.72322772097",
                    "longitude": "11.43305",
                    "latitude": "51.94429",
                    "telefon": "+49 39268 2365",
                    "fax": [],
                    "email": [],
                    "startdatum": "09.07.2025",
                    "startzeit": "08:00",
                    "enddatum": "10.07.2025",
                    "endzeit": "08:00"
                },
                {
                    "name": "Marktapotheke Bernburg",
                    "kammer": "aksa",
                    "id": "616",
                    "apo_id": "aksa616",
                    "strasse": "Markt 31",
                    "plz": "06406",
                    "ort": "Bernburg",
                    "distanz": "23.59277230857",
                    "longitude": "11.73696",
                    "latitude": "51.79808",
                    "telefon": "+49 3471 350624",
                    "fax": [],
                    "email": [],
                    "startdatum": "09.07.2025",
                    "startzeit": "08:00",
                    "enddatum": "10.07.2025",
                    "endzeit": "08:00"
                }
            ]
        }
    }
}