{
    "alerts": [],
    "settings": {
        "interface": "emergency",
        "singleViewUid": "261"
    },
    "args": {
        "action": "result",
        "controller": "Search",
        "search": {
            "date": "2025-07-12",
            "lat": "",
            "lng": "",
            "plzort": "Baden-Württemberg",
            "radius": "25",
            "street": ""
        },
        "token": "216823d96ea25c051509d935955c130fbc72680fc1d3040fe3e8ca0e25f9cd02"
    },
    "results": {
        "parameter": {
            "plzort": "Baden-Württemberg",
            "strasse": [],
            "radius": "25.0",
            "longitude": "9.041169",
            "latitude": "48.537749999999996",
            "limit": [],
            "datum": "11.07.2025"
        },
        "statistik": {
            "anzahl": 15
        },
        "quota": {
            "verwendet": "248"
        },
        "apotheken": {
            "apotheke": [
                {
                    "name": "ina Apotheke Stadt",
                    "kammer": "lakbw",
                    "id": "1672006",
                    "apo_id": "lakbw1672006",
                    "strasse": "Am Lustnauer Tor 4",
                    "plz": "72074",
                    "ort": "Tübingen",
                    "distanz": "2.19763463005",
                    "longitude": "9.0577678",
                    "latitude": "48.5213481",
                    "telefon": "+49 7071 51030",
                    "fax": "+49 7071 26328",
                    "email": [],
                    "startdatum": "11.07.2025",
                    "startzeit": "08:30",
                    "enddatum": "12.07.2025",
                    "endzeit": "08:30"
                },
                {
                    "name": "Alamannen-Apotheke Holzgerlingen",
                    "kammer": "lakbw",
                    "id": "1295001",
                    "apo_id": "lakbw1295001",
                    "strasse": "Tübinger Str. 11",
                    "plz": "71088",
                    "ort": "Holzgerlingen",
                    "distanz": "11.42290495838",
                    "longitude": "9.0119101",
                    "latitude": "48.6386217",
                    "telefon": "+49 7031 689930",
                    "fax": "+49 7031 689950",
                    "email": [],
                    "startdatum": "11.07.2025",
                    "startzeit": "08:30",
                    "enddatum": "12.07.2025",
                    "endzeit": "08:30"
                },
                {
                    "name": "Hirsch Apotheke Mache Reutlingen",
                    "kammer": "lakbw",
                    "id": "1553012",
                    "apo_id": "lakbw1553012",
                    "strasse": "Wilhelmstr. 53",
                    "plz": "72764",
                    "ort": "Reutlingen",
                    "distanz": "13.50843701384",
                    "longitude": "9.2111224",
                    "latitude": "48.492944",
                    "telefon": "+49 7121 334937",
                    "fax": "+49 7121 310774",
                    "email": [],
                    "startdatum": "11.07.2025",
                    "startzeit": "08:30",
                    "enddatum": "12.07.2025",
                    "endzeit": "08:30"
                },
                {
                    "name": "Schwarzwald-Apotheke Herrenberg",
                    "kammer": "lakbw",
                    "id": "1284007",
                    "apo_id": "lakbw1284007",
                    "strasse": "Nagolder Str. 27",
                    "plz": "71083",
                    "ort": "Herrenberg",
                    "distanz": "14.72459344578",
                    "longitude": "8.86173",
                    "latitude": "48.59563",
                    "telefon": "+49 7032 26111",
                    "fax": "+49 7032 287100",
                    "email": [],
                    "startdatum": "11.07.2025",
                    "startzeit": "08:30",
                    "enddatum": "12.07.2025",
                    "endzeit": "08:30"
                },
                {
                    "name": "Linden-Apotheke Bempflingen",
                    "kammer": "lakbw",
                    "id": "1071001",
                    "apo_id": "lakbw1071001",
                    "strasse": "Lindenstr. 13",
                    "plz": "72658",
                    "ort": "Bempflingen",
                    "distanz": "17.08309686026",
                    "longitude": "9.2666703",
                    "latitude": "48.5722468",
                    "telefon": "+49 7123 932409",
                    "fax": "+49 7123 932372",
                    "email": [],
                    "startdatum": "11.07.2025",
                    "startzeit": "08:30",
                    "enddatum": "12.07.2025",
                    "endzeit": "08:30"
                },
                {
                    "name": "Neue Apotheke Echterdingen",
                    "kammer": "lakbw",
                    "id": "1387006",
                    "apo_id": "lakbw1387006",
                    "strasse": "Hauptstr. 44",
                    "plz": "70771",
                    "ort": "Leinfelden-Echterdingen",
                    "distanz": "18.985452029610002",
                    "longitude": "9.1668082",
                    "latitude": "48.6867724",
                    "telefon": "+49 711 7949910",
                    "fax": "+49 711 7949930",
                    "email": [],
                    "startdatum": "11.07.2025",
                    "startzeit": "08:30",
                    "enddatum": "12.07.2025",
                    "endzeit": "08:30"
                },
                {
                    "name": "Laurentius Apotheke Maichingen",
                    "kammer": "lakbw",
                    "id": "1588010",
                    "apo_id": "lakbw1588010",
                    "strasse": "Laurentiusstr. 24",
                    "plz": "71069",
                    "ort": "Sindelfingen",
                    "distanz": "21.388717708970002",
                    "longitude": "8.9655617",
                    "latitude": "48.7234461",
                    "telefon": "+49 7031 382365",
                    "fax": "+49 7031 682603",
                    "email": [],
                    "startdatum": "11.07.2025",
                    "startzeit": "08:30",
                    "enddatum": "12.07.2025",
                    "endzeit": "08:30"
                },
                {
                    "name": "Sonnen-Apotheke Hechingen",
                    "kammer": "lakbw",
                    "id": "1819248",
                    "apo_id": "lakbw1819248",
                    "strasse": "Weilheimer Str. 31",
                    "plz": "72379",
                    "ort": "Hechingen",
                    "distanz": "22.251326542850002",
                    "longitude": "8.95548",
                    "latitude": "48.34594",
                    "telefon": "+49 7471 9757562",
                    "fax": "+49 7471 9757564",
                    "email": [],
                    "startdatum": "11.07.2025",
                    "startzeit": "08:30",
                    "enddatum": "12.07.2025",
                    "endzeit": "08:30"
                },
                {
                    "name": "Rosen-Apotheke Wolfschlugen",
                    "kammer": "lakbw",
                    "id": "1752001",
                    "apo_id": "lakbw1752001",
                    "strasse": "Nürtinger Str. 4",
                    "plz": "72649",
                    "ort": "Wolfschlugen",
                    "distanz": "22.2955567683",
                    "longitude": "9.2885147",
                    "latitude": "48.6529883",
                    "telefon": "+49 7022 54411",
                    "fax": "+49 7022 54809",
                    "email": [],
                    "startdatum": "11.07.2025",
                    "startzeit": "08:30",
                    "enddatum": "12.07.2025",
                    "endzeit": "08:30"
                },
                {
                    "name": "Killertal-Apotheke Jungingen",
                    "kammer": "lakbw",
                    "id": "1321001",
                    "apo_id": "lakbw1321001",
                    "strasse": "Killertalstr. 6",
                    "plz": "72417",
                    "ort": "Jungingen",
                    "distanz": "23.49629430029",
                    "longitude": "9.0424942",
                    "latitude": "48.3264518",
                    "telefon": "+49 7477 633",
                    "fax": "+49 7477 91256",
                    "email": [],
                    "startdatum": "11.07.2025",
                    "startzeit": "08:30",
                    "enddatum": "12.07.2025",
                    "endzeit": "08:30"
                },
                {
                    "name": "Waldau-Apotheke Degerloch",
                    "kammer": "lakbw",
                    "id": "1653173",
                    "apo_id": "lakbw1653173",
                    "strasse": "Epplestr. 3",
                    "plz": "70597",
                    "ort": "Stuttgart",
                    "distanz": "25.31248441899",
                    "longitude": "9.169926",
                    "latitude": "48.7487771",
                    "telefon": "+49 711 760624",
                    "fax": "+49 711 7657913",
                    "email": [],
                    "startdatum": "11.07.2025",
                    "startzeit": "08:30",
                    "enddatum": "12.07.2025",
                    "endzeit": "08:30"
                },
                {
                    "name": "Bihlplatz-Apotheke",
                    "kammer": "lakbw",
                    "id": "1653036",
                    "apo_id": "lakbw1653036",
                    "strasse": "Böblinger Str. 164",
                    "plz": "70199",
                    "ort": "Stuttgart",
                    "distanz": "26.0412193821",
                    "longitude": "9.1517",
                    "latitude": "48.76018",
                    "telefon": "+49 711 6402884",
                    "fax": "+49 711 6403549",
                    "email": [],
                    "startdatum": "11.07.2025",
                    "startzeit": "08:30",
                    "enddatum": "12.07.2025",
                    "endzeit": "08:30"
                },
                {
                    "name": "Eichen-Apotheke Calw",
                    "kammer": "lakbw",
                    "id": "1120009",
                    "apo_id": "lakbw1120009",
                    "strasse": "Gartenstr. 1",
                    "plz": "75365",
                    "ort": "Calw",
                    "distanz": "26.68258656511",
                    "longitude": "8.767721",
                    "latitude": "48.6949176",
                    "telefon": "+49 7051 30709",
                    "fax": "+49 7051 3207",
                    "email": [],
                    "startdatum": "11.07.2025",
                    "startzeit": "08:30",
                    "enddatum": "12.07.2025",
                    "endzeit": "08:30"
                },
                {
                    "name": "Kur-Apotheke Beuren",
                    "kammer": "lakbw",
                    "id": "1078001",
                    "apo_id": "lakbw1078001",
                    "strasse": "Linsenhofer Str. 28",
                    "plz": "72660",
                    "ort": "Beuren",
                    "distanz": "26.84195183556",
                    "longitude": "9.4015",
                    "latitude": "48.57004",
                    "telefon": "+49 7025 6686",
                    "fax": "+49 7025 7974",
                    "email": [],
                    "startdatum": "11.07.2025",
                    "startzeit": "08:30",
                    "enddatum": "12.07.2025",
                    "endzeit": "08:30"
                },
                {
                    "name": "Apotheke in der Kirchstraße",
                    "kammer": "lakbw",
                    "id": "1819293",
                    "apo_id": "lakbw1819293",
                    "strasse": "Kirchstr. 5",
                    "plz": "72574",
                    "ort": "Bad Urach",
                    "distanz": "26.853122846170002",
                    "longitude": "9.3982701",
                    "latitude": "48.4927299",
                    "telefon": "+49 7125 9437770",
                    "fax": "+49 7125 9437771",
                    "email": [],
                    "startdatum": "11.07.2025",
                    "startzeit": "08:30",
                    "enddatum": "12.07.2025",
                    "endzeit": "08:30"
                }
            ]
        }
    }
}