{
  "Berlin": [
    {
      "eczaneAdi": "Galenus-Apotheke",
      "adres": "Reinhardtstr. 5, 10117 Berlin",
      "telefon": "+49 30 2827871",
      "enlem": "52.5236486",
      "boylam": "13.3868064",
      "mesafe": "0.7 km"
    },
    {
      "eczaneAdi": "Immanuel-Apotheke",
      "adres": "Immanuelkirchstr. 2, 10405 Berlin",
      "telefon": "+49 30 40056757",
      "enlem": "52.5329883",
      "boylam": "13.4223071",
      "mesafe": "2.9 km"
    },
    {
      "eczaneAdi": "Quartier Apotheke Nolleturm",
      "adres": "Nollendorfplatz3-4, 10777 Berlin",
      "telefon": "+49 30 21280180",
      "enlem": "52.4994278",
      "boylam": "13.3521517",
      "mesafe": "3.2 km"
    },
    {
      "eczaneAdi": "Europa-Apotheke",
      "adres": "Karl-Marx-Allee 90 A, 10243 Berlin",
      "telefon": "+49 30 29492699",
      "enlem": "52.5163851",
      "boylam": "13.4412082",
      "mesafe": "3.6 km"
    },
    {
      "eczaneAdi": "Apotheke im Gesundbrunnen-Center",
      "adres": "Badstr. 4, 13357 Berlin",
      "telefon": "+49 30 49760419",
      "enlem": "52.549678",
      "boylam": "13.3879517",
      "mesafe": "3.6 km"
    },
    {
      "eczaneAdi": "Märkische Apotheke",
      "adres": "Müllerstr. 33, 13353 Berlin",
      "telefon": "+49 30 4566144",
      "enlem": "52.5484",
      "boylam": "13.35625",
      "mesafe": "4.1 km"
    },
    {
      "eczaneAdi": "Pannier-Apotheke",
      "adres": "Sonnenallee 31-33, 12047 Berlin",
      "telefon": "+49 30 61309443",
      "enlem": "52.4863598",
      "boylam": "13.4299875",
      "mesafe": "4.4 km"
    },
    {
      "eczaneAdi": "Atlantis-Apotheke",
      "adres": "Wilmersdorfer Str. 31, 10585 Berlin",
      "telefon": "+49 30 3422926",
      "enlem": "52.5130938",
      "boylam": "13.3047415",
      "mesafe": "5.7 km"
    },
    {
      "eczaneAdi": "Flora-Apotheke",
      "adres": "Berliner Allee 109, 13088 Berlin",
      "telefon": "+49 30 9250107",
      "enlem": "52.5504401",
      "boylam": "13.4597209",
      "mesafe": "6.1 km"
    },
    {
      "eczaneAdi": "Mendel-Apotheke",
      "adres": "Breite Str. 6, 13187 Berlin",
      "telefon": "+49 30 47473101",
      "enlem": "52.57149",
      "boylam": "13.4105899",
      "mesafe": "6.2 km"
    },
    {
      "eczaneAdi": "Luna-Apotheke",
      "adres": "Am Treptower Park 40-42, 12435 Berlin",
      "telefon": "+49 30 53698100",
      "enlem": "52.48549",
      "boylam": "13.46577",
      "mesafe": "6.3 km"
    },
    {
      "eczaneAdi": "Sky Apotheke am Kudamm",
      "adres": "Kurfürstendamm 139, 10711 Berlin",
      "telefon": "+49 30 8927694",
      "enlem": "52.4976163",
      "boylam": "13.2956155",
      "mesafe": "6.7 km"
    },
    {
      "eczaneAdi": "Arcaden-Apotheke am Tempelhofer Hafen",
      "adres": "Tempelhofer Damm 227, 12099 Berlin",
      "telefon": "+49 30 75654080",
      "enlem": "52.455587",
      "boylam": "13.3858907",
      "mesafe": "6.8 km"
    },
    {
      "eczaneAdi": "Titania-Apotheke",
      "adres": "Markelstr. 3, 12163 Berlin",
      "telefon": "+49 30 7917091",
      "enlem": "52.4637124",
      "boylam": "13.3262204",
      "mesafe": "7.3 km"
    },
    {
      "eczaneAdi": "Südend-Apotheke",
      "adres": "Steglitzer Damm 68, 12169 Berlin",
      "telefon": "+49 30 79780070",
      "enlem": "52.4497",
      "boylam": "13.34806",
      "mesafe": "8.0 km"
    },
    {
      "eczaneAdi": "Pfauen-Apotheke",
      "adres": "Rudower Str. 27-29, 12351 Berlin",
      "telefon": "+49 30 6019025",
      "enlem": "52.4412513",
      "boylam": "13.4590549",
      "mesafe": "9.7 km"
    },
    {
      "eczaneAdi": "Sonnenschein-Apotheke",
      "adres": "Treskowallee 128, 10318 Berlin",
      "telefon": "+49 30 50378600",
      "enlem": "52.4788009",
      "boylam": "13.5243733",
      "mesafe": "10.1 km"
    },
    {
      "eczaneAdi": "Sanitas Apotheke",
      "adres": "Oraniendamm 10-6, 13469 Berlin",
      "telefon": "+49 30 40396922",
      "enlem": "52.6075045",
      "boylam": "13.3255993",
      "mesafe": "10.9 km"
    },
    {
      "eczaneAdi": "Berolina-Apotheke",
      "adres": "Clayallee 345, 14169 Berlin",
      "telefon": "+49 30 8099600",
      "enlem": "52.4363758",
      "boylam": "13.2605912",
      "mesafe": "12.5 km"
    },
    {
      "eczaneAdi": "Askanier-Apotheke",
      "adres": "Streitstr. 11-14, 13587 Berlin",
      "telefon": "+49 30 3352680",
      "enlem": "52.556849",
      "boylam": "13.2097988",
      "mesafe": "12.9 km"
    },
    {
      "eczaneAdi": "Apotheke am Stadtrand",
      "adres": "Ahrensfelder Chaussee 146 A, 12689 Berlin",
      "telefon": "+49 30 9375468",
      "enlem": "52.5708",
      "boylam": "13.56337",
      "mesafe": "13.3 km"
    },
    {
      "eczaneAdi": "Neue Roland Apotheke",
      "adres": "Oranienburger Chaussee 17, 16548 Glienicke/Nordbahn",
      "telefon": "033056 94500",
      "enlem": "52.63325",
      "boylam": "13.30969",
      "mesafe": "14.0 km"
    },
    {
      "eczaneAdi": "Apotheke am Markt",
      "adres": "Bekassinenweg 18, 13503 Berlin",
      "telefon": "+49 30 4311247",
      "enlem": "52.6076219",
      "boylam": "13.2349401",
      "mesafe": "14.5 km"
    },
    {
      "eczaneAdi": "Puls-Apotheke",
      "adres": "Goltzstr. 39, 12307 Berlin",
      "telefon": "+49 30 70784791",
      "enlem": "52.3871212",
      "boylam": "13.4093607",
      "mesafe": "14.5 km"
    },
    {
      "eczaneAdi": "Kaufpark Apotheke",
      "adres": "Landsberger Chaussee 17, 16356 Ahrensfelde - OT Eiche-Süd",
      "telefon": "+49 30 9989607",
      "enlem": "52.5497144",
      "boylam": "13.5988534",
      "mesafe": "14.7 km"
    }
  ],
  "Nordrhein-Westfalen": [
    {
      "eczaneAdi": "Pinguin-Apotheke",
      "adres": "Hermannstr. 29, 44263 Dortmund",
      "telefon": "0231/422068",
      "enlem": "51.4889517",
      "boylam": "7.4996935",
      "mesafe": "4.0 km"
    },
    {
      "eczaneAdi": "Zeppelin-Apotheke",
      "adres": "Beurhausstr. 21, 44137 Dortmund",
      "telefon": "0231/140754",
      "enlem": "51.5092782",
      "boylam": "7.4588719",
      "mesafe": "7.4 km"
    },
    {
      "eczaneAdi": "Fleming-Apotheke",
      "adres": "Harkortstr. 38, 44225 Dortmund",
      "telefon": "0231/793005-0",
      "enlem": "51.4753347",
      "boylam": "7.4423687",
      "mesafe": "7.8 km"
    },
    {
      "eczaneAdi": "Robin-Apotheke im real,-",
      "adres": "Kabeler Str. 25, 58099 Hagen",
      "telefon": "02331/4833388",
      "enlem": "51.4084945",
      "boylam": "7.4751384",
      "mesafe": "9.6 km"
    },
    {
      "eczaneAdi": "Dorf-Apotheke",
      "adres": "Heidestr. 61, 58708 Menden",
      "telefon": "02373/63637",
      "enlem": "51.4564758",
      "boylam": "7.7568589",
      "mesafe": "14.3 km"
    },
    {
      "eczaneAdi": "St. Barbara-Apotheke",
      "adres": "Schulstr. 45, 59192 Bergkamen",
      "telefon": "02307/69761",
      "enlem": "51.6073393",
      "boylam": "7.6190368",
      "mesafe": "15.0 km"
    },
    {
      "eczaneAdi": "Apotheke im Kaufland",
      "adres": "Theodor-Heuss-Ring 11 - 25, 58636 Iserlohn",
      "telefon": "02371/95350",
      "enlem": "51.3762172",
      "boylam": "7.6993458",
      "mesafe": "15.2 km"
    },
    {
      "eczaneAdi": "Feen-Apotheke",
      "adres": "Kaiserstr. 123, 58300 Wetter",
      "telefon": "02335/8468426",
      "enlem": "51.3841742",
      "boylam": "7.3919268",
      "mesafe": "15.5 km"
    },
    {
      "eczaneAdi": "Glückauf-Apotheke",
      "adres": "Wittener Str. 60, 45711 Datteln",
      "telefon": "02363/62176",
      "enlem": "51.61955",
      "boylam": "7.31914",
      "mesafe": "22.6 km"
    },
    {
      "eczaneAdi": "farma-plus Apotheke Glückauf",
      "adres": "Herner Str. 349, 44807 Bochum",
      "telefon": "+49 234 531467",
      "enlem": "51.50805",
      "boylam": "7.21142",
      "mesafe": "24.0 km"
    },
    {
      "eczaneAdi": "Bären-Apotheke",
      "adres": "Hattinger Str. 243, 44795 Bochum",
      "telefon": "0234/430024",
      "enlem": "51.46136",
      "boylam": "7.20169",
      "mesafe": "24.6 km"
    },
    {
      "eczaneAdi": "Apotheke am Sandforter Weg",
      "adres": "Sandforter Weg 9, 59379 Selm",
      "telefon": "+49 2592 3097",
      "enlem": "51.69517",
      "boylam": "7.46212",
      "mesafe": "24.9 km"
    },
    {
      "eczaneAdi": "Glückauf-Apotheke",
      "adres": "König-Ludwig-Str. 96, 45663 Recklinghausen",
      "telefon": "02361/34368",
      "enlem": "51.5789944",
      "boylam": "7.2262564",
      "mesafe": "25.3 km"
    }
  ],
  "Hamburg": [
    {
      "eczaneAdi": "Fritz-Reuter Apotheke",
      "adres": "Mozartstraße 16, 22083 Hamburg",
      "telefon": "+49 40 2201785",
      "enlem": "53.5773871",
      "boylam": "10.0209121",
      "mesafe": "3.3 km"
    },
    {
      "eczaneAdi": "Eimsbütteler-Apotheke",
      "adres": "Osterstraße 16, 20259 Hamburg",
      "telefon": "+49 40 4922060",
      "enlem": "53.5739221",
      "boylam": "9.9612585",
      "mesafe": "3.7 km"
    },
    {
      "eczaneAdi": "Schiller-Apotheke",
      "adres": "Neue Große Bergstraße 7, 22767 Hamburg",
      "telefon": "+49 40 3806868",
      "enlem": "53.5519752",
      "boylam": "9.9381041",
      "mesafe": "4.1 km"
    },
    {
      "eczaneAdi": "Pasteur-Apotheke",
      "adres": "Alsterdorfer Straße 175, 22297 Hamburg",
      "telefon": "+49 40 5133266",
      "enlem": "53.60486",
      "boylam": "9.99937",
      "mesafe": "6.1 km"
    },
    {
      "eczaneAdi": "Apotheke am Billstedter Platz",
      "adres": "Billstedter Platz 9, 22111 Hamburg",
      "telefon": "+49 40 7322222",
      "enlem": "53.5418471",
      "boylam": "10.1064762",
      "mesafe": "7.1 km"
    },
    {
      "eczaneAdi": "Karlshöher-Apotheke",
      "adres": "Pezolddamm 141, 22175 Hamburg",
      "telefon": "+49 40 6404706",
      "enlem": "53.624797",
      "boylam": "10.1130165",
      "mesafe": "11.1 km"
    },
    {
      "eczaneAdi": "Markt Apotheke Neugraben",
      "adres": "Marktpassage 7, 21149 Hamburg",
      "telefon": "+49 40 7010060",
      "enlem": "53.4710482",
      "boylam": "9.8527513",
      "mesafe": "13.2 km"
    },
    {
      "eczaneAdi": "Markt Apotheke",
      "adres": "Markt 5, 21509 Glinde",
      "telefon": "040-7106021",
      "enlem": "53.5418259",
      "boylam": "10.213868",
      "mesafe": "14.2 km"
    },
    {
      "eczaneAdi": "Tarpenbek-Apotheke",
      "adres": "Am Tarpenufer 6, 22848 Norderstedt",
      "telefon": "040-5296995",
      "enlem": "53.681352",
      "boylam": "9.9977624",
      "mesafe": "14.6 km"
    },
    {
      "eczaneAdi": "Pluspunkt-Apotheke am Sachsentor",
      "adres": "Sachsentor 29-31, 21029 Hamburg",
      "telefon": "+49 40 7211010",
      "enlem": "53.4880432",
      "boylam": "10.2130606",
      "mesafe": "15.7 km"
    },
    {
      "eczaneAdi": "Bergstedter Markt-Apotheke",
      "adres": "Bergstedter Markt 15, 22395 Hamburg",
      "telefon": "+49 40 6046463",
      "enlem": "53.67148",
      "boylam": "10.12406",
      "mesafe": "15.8 km"
    },
    {
      "eczaneAdi": "Olympia-Apotheke",
      "adres": "Heinr.-Christiansen-Str. 41, 25421 Pinneberg",
      "telefon": "04101-54480",
      "enlem": "53.652376",
      "boylam": "9.7904656",
      "mesafe": "18.0 km"
    },
    {
      "eczaneAdi": "Accent-Apotheke",
      "adres": "Große Str. 30, 22926 Ahrensburg",
      "telefon": "04102-467580",
      "enlem": "53.6741226",
      "boylam": "10.2387206",
      "mesafe": "20.9 km"
    },
    {
      "eczaneAdi": "Sonnen-Apotheke",
      "adres": "Dibberser Mühlenweg 1 a, 21244 Buchholz in der Nordheide",
      "telefon": "+49 4181 31743",
      "enlem": "53.3332641",
      "boylam": "9.8745667",
      "mesafe": "25.6 km"
    },
    {
      "eczaneAdi": "wir leben-Apotheke am Bahnhof",
      "adres": "Bahnhofstr. 67, 21423 Winsen (Luhe)",
      "telefon": "+49 4171 71460",
      "enlem": "53.3556573",
      "boylam": "10.2061221",
      "mesafe": "25.6 km"
    },
    {
      "eczaneAdi": "Engel Apotheke",
      "adres": "Cuxhavener Str. 163, 21614 Buxtehude",
      "telefon": "+49 4163 8264888",
      "enlem": "53.4829732",
      "boylam": "9.6267881",
      "mesafe": "25.9 km"
    },
    {
      "eczaneAdi": "Alster-Apotheke",
      "adres": "Neuer Weg 24, 24558 Henstedt-Ulzburg",
      "telefon": "04193-2030",
      "enlem": "53.7889369",
      "boylam": "10.0010477",
      "mesafe": "26.6 km"
    },
    {
      "eczaneAdi": "Adler-Apotheke",
      "adres": "Rathausstr. 33, 22941 Bargteheide",
      "telefon": "04532-1719",
      "enlem": "53.73035",
      "boylam": "10.26856",
      "mesafe": "26.7 km"
    }
  ],
  "Baden-Württemberg": [
    {
      "eczaneAdi": "Post-Apotheke Tübingen",
      "adres": "Europaplatz 3, 72072 Tübingen",
      "telefon": "+49 7071 32777",
      "enlem": "48.5163388",
      "boylam": "9.0583954",
      "mesafe": "2.7 km"
    },
    {
      "eczaneAdi": "Rathaus-Apotheke Kirchentellinsfurt",
      "adres": "Dorfstr. 41, 72138 Kirchentellinsfurt",
      "telefon": "+49 7121 96880",
      "enlem": "48.5319196",
      "boylam": "9.1480319",
      "mesafe": "7.9 km"
    },
    {
      "eczaneAdi": "Apotheke Ohmenhausen",
      "adres": "Gomaringer Str. 33, 72770 Reutlingen",
      "telefon": "+49 7121 91660",
      "enlem": "48.4760818",
      "boylam": "9.1367",
      "mesafe": "9.8 km"
    },
    {
      "eczaneAdi": "Central-Apotheke Schönaich",
      "adres": "Wettgasse 45, 71101 Schönaich",
      "telefon": "+49 7031 651388",
      "enlem": "48.6562355",
      "boylam": "9.0598771",
      "mesafe": "13.2 km"
    },
    {
      "eczaneAdi": "Bären Apotheke Herrenberg",
      "adres": "Hindenburgstr. 20, 71083 Herrenberg",
      "telefon": "+49 7032 122110",
      "enlem": "48.594684",
      "boylam": "8.8695929",
      "mesafe": "14.2 km"
    },
    {
      "eczaneAdi": "Eichenberg-Apotheke Hirrlingen",
      "adres": "Marktstr. 5, 72145 Hirrlingen",
      "telefon": "+49 7478 91170",
      "enlem": "48.41046",
      "boylam": "8.88757",
      "mesafe": "18.1 km"
    },
    {
      "eczaneAdi": "Bahnhof-Apotheke Metzingen",
      "adres": "Schönbeinstr. 20, 72555 Metzingen",
      "telefon": "+49 7123 14252",
      "enlem": "48.5394308",
      "boylam": "9.2884493",
      "mesafe": "18.3 km"
    },
    {
      "eczaneAdi": "Rotbühl-Apotheke Sindelfingen",
      "adres": "Leonberger Str. 29, 71063 Sindelfingen",
      "telefon": "+49 7031 70820",
      "enlem": "48.7162673",
      "boylam": "9.002642",
      "mesafe": "20.1 km"
    },
    {
      "eczaneAdi": "Apotheke in der SchwabenGalerie",
      "adres": "Schwabenplatz 1, 70563 Stuttgart",
      "telefon": "+49 711 9976900",
      "enlem": "48.7301521",
      "boylam": "9.1089",
      "mesafe": "22.0 km"
    },
    {
      "eczaneAdi": "Kronen-Apotheke Neuhausen",
      "adres": "Marktstr. 3, 73765 Neuhausen auf den Fildern",
      "telefon": "+49 7158 67000",
      "enlem": "48.68466",
      "boylam": "9.27955",
      "mesafe": "24.0 km"
    },
    {
      "eczaneAdi": "Uhland-Apotheke Nürtingen",
      "adres": "Uhlandstr. 3, 72622 Nürtingen",
      "telefon": "+49 7022 8633",
      "enlem": "48.6270619",
      "boylam": "9.3402263",
      "mesafe": "24.2 km"
    }
  ],
  "Bayern": [
    {
      "eczaneAdi": "St. Georgs-Apotheke",
      "adres": "Frankenring 5, 85110 Kipfenberg",
      "telefon": "+49 8465 1065",
      "enlem": "48.9495793",
      "boylam": "11.3938895",
      "mesafe": "0.8 km"
    },
    {
      "eczaneAdi": "Spitalstadt-Apotheke",
      "adres": "Am Anger 4, 85072 Eichstätt",
      "telefon": "+49 8421 9097200",
      "enlem": "48.8931655",
      "boylam": "11.1805398",
      "mesafe": "17.4 km"
    },
    {
      "eczaneAdi": "Apotheke im Westpark",
      "adres": "Am Westpark 6, 85057 Ingolstadt",
      "telefon": "+49 841 493030",
      "enlem": "48.7745991",
      "boylam": "11.3889437",
      "mesafe": "19.2 km"
    },
    {
      "eczaneAdi": "Agnes-Bernauer-Apotheke",
      "adres": "Griesstr. 1, 85088 Vohburg",
      "telefon": "+49 8457 1000",
      "enlem": "48.769524",
      "boylam": "11.618864",
      "mesafe": "25.2 km"
    }
  ],
  "Brandenburg": [
    {
      "eczaneAdi": "Luisen-Apotheke",
      "adres": "Berliner Straße 94, 16515 Oranienburg",
      "telefon": "03301 / 535 003",
      "enlem": "52.7434803",
      "boylam": "13.2388483",
      "mesafe": "11.4 km"
    },
    {
      "eczaneAdi": "Kloster Apotheke Zehdenick Kloster Apotheke OHG",
      "adres": "Berliner Straße 39, 16792 Zehdenick",
      "telefon": "03307   / 3433",
      "enlem": "52.97877",
      "boylam": "13.3322095",
      "mesafe": "15.9 km"
    },
    {
      "eczaneAdi": "Vitalis Apotheke",
      "adres": "Rosa-Luxemburg-Straße 51, 16727 Velten",
      "telefon": "+49 3304 505794",
      "enlem": "52.67962",
      "boylam": "13.17222",
      "mesafe": "19.1 km"
    },
    {
      "eczaneAdi": "Sorella Apotheke",
      "adres": "Berliner Straße 27, 16540 Hohen Neuendorf",
      "telefon": "+49 3303 2957010",
      "enlem": "52.66857",
      "boylam": "13.28191",
      "mesafe": "19.8 km"
    },
    {
      "eczaneAdi": "Neue Roland Apotheke",
      "adres": "Oranienburger Chaussee 17, 16548 Glienicke/Nordbahn",
      "telefon": "033056 94500",
      "enlem": "52.63325",
      "boylam": "13.30969",
      "mesafe": "24.0 km"
    },
    {
      "eczaneAdi": "Apotheke am Markt",
      "adres": "Bekassinenweg 18, 13503 Berlin",
      "telefon": "+49 30 4311247",
      "enlem": "52.6076219",
      "boylam": "13.2349401",
      "mesafe": "26.5 km"
    },
    {
      "eczaneAdi": "Sanitas Apotheke",
      "adres": "Oraniendamm 10-6, 13469 Berlin",
      "telefon": "+49 30 40396922",
      "enlem": "52.6075045",
      "boylam": "13.3255993",
      "mesafe": "27.0 km"
    }
  ],
  "Bremen": [
    {
      "eczaneAdi": "Vital-Apotheke im Fachärztezentrum-Nord",
      "adres": "Hammersbecker Str. 224, 28755 Bremen",
      "telefon": "+49 421 6203620",
      "enlem": "53.1844073",
      "boylam": "8.5937461",
      "mesafe": "8.0 km"
    },
    {
      "eczaneAdi": "Roland-Apotheke",
      "adres": "Hemmstr. 231, 28215 Bremen",
      "telefon": "+49 421 351955",
      "enlem": "53.0950854",
      "boylam": "8.8093161",
      "mesafe": "9.5 km"
    },
    {
      "eczaneAdi": "Moorkamp-Apotheke",
      "adres": "Brendelweg 5, 27755 Delmenhorst",
      "telefon": "+49 4221 25055",
      "enlem": "53.032369",
      "boylam": "8.6228754",
      "mesafe": "13.4 km"
    },
    {
      "eczaneAdi": "Hubertus-Apotheke",
      "adres": "Borgfelder Heerstr. 28 A, 28357 Bremen",
      "telefon": "+49 421 270229",
      "enlem": "53.12282",
      "boylam": "8.89932",
      "mesafe": "14.0 km"
    },
    {
      "eczaneAdi": "Schleng-Apotheke",
      "adres": "Schlengstr. 31, 28309 Bremen",
      "telefon": "+49 421 452215",
      "enlem": "53.0508237",
      "boylam": "8.8939178",
      "mesafe": "17.0 km"
    },
    {
      "eczaneAdi": "Apotheke am Markt",
      "adres": "Weberweg 2, 28844 Weyhe",
      "telefon": "+49 4203 1300",
      "enlem": "52.98135",
      "boylam": "8.84978",
      "mesafe": "21.0 km"
    },
    {
      "eczaneAdi": "Geest-Apotheke Wallhöfen",
      "adres": "Wallhöfener Str. 62, 27729 Vollersode",
      "telefon": "+49 4793 953445",
      "enlem": "53.3174341",
      "boylam": "8.8706177",
      "mesafe": "22.6 km"
    },
    {
      "eczaneAdi": "Storchen-Apotheke",
      "adres": "Uphuser Heerstr. 35, 28832 Achim",
      "telefon": "+49 4202 910150",
      "enlem": "53.0273012",
      "boylam": "8.9743033",
      "mesafe": "22.9 km"
    },
    {
      "eczaneAdi": "Sonnen-Apotheke",
      "adres": "Breite Str. 56, 26919 Brake",
      "telefon": "+49 4401 4485",
      "enlem": "53.326394",
      "boylam": "8.4790649",
      "mesafe": "24.8 km"
    },
    {
      "eczaneAdi": "Wilstedter Apotheke",
      "adres": "Am Brink 1, 27412 Wilstedt",
      "telefon": "+49 4283 5390",
      "enlem": "53.19582",
      "boylam": "9.09069",
      "mesafe": "27.2 km"
    },
    {
      "eczaneAdi": "Geest-Apotheke",
      "adres": "Hauptstr. 20, 27801 Dötlingen",
      "telefon": "+49 4432 94233",
      "enlem": "52.9749282",
      "boylam": "8.3978022",
      "mesafe": "27.4 km"
    }
  ],
  "Hessen": [
    {
      "eczaneAdi": "Engel Apotheke",
      "adres": "Bahnhofstr. 2, 35321 Laubach",
      "telefon": "+49 6405 91230",
      "enlem": "50.54201",
      "boylam": "8.98976",
      "mesafe": "7.8 km"
    },
    {
      "eczaneAdi": "Storchen Apotheke",
      "adres": "Rabenauer Str. 24, 35396 Gießen",
      "telefon": "+49 641 51504",
      "enlem": "50.6051461",
      "boylam": "8.7048416",
      "mesafe": "22.9 km"
    },
    {
      "eczaneAdi": "Deine Apotheke Linden",
      "adres": "Robert-Bosch-Straße 6, 35440 Linden",
      "telefon": "+49 6403 609820",
      "enlem": "50.53802",
      "boylam": "8.65095",
      "mesafe": "27.9 km"
    },
    {
      "eczaneAdi": "Erlenring Apotheke",
      "adres": "Erlenring 9, 35037 Marburg",
      "telefon": "+49 6421 1664100",
      "enlem": "50.80676",
      "boylam": "8.77737",
      "mesafe": "28.3 km"
    },
    {
      "eczaneAdi": "Wartenberg Apotheke",
      "adres": "Rudloser Str. 1, 36367 Wartenberg",
      "telefon": "+49 6641 62876",
      "enlem": "50.6274902",
      "boylam": "9.444884",
      "mesafe": "29.6 km"
    },
    {
      "eczaneAdi": "Amtsapotheke",
      "adres": "Bingenheimer Str. 34, 61203 Reichelsheim (Wetterau)",
      "telefon": "+49 6035 3216",
      "enlem": "50.3588437",
      "boylam": "8.8750513",
      "mesafe": "29.8 km"
    },
    {
      "eczaneAdi": "Apotheke Rodheim-Bieber",
      "adres": "Mühlbergstr. 7, 35444 Biebertal",
      "telefon": "+49 6409 6351",
      "enlem": "50.6199",
      "boylam": "8.5959007",
      "mesafe": "30.6 km"
    },
    {
      "eczaneAdi": "Dilltal-Apotheke im Gesundheitszentrum Hermannstein",
      "adres": "Loherstraße 1, 35586 Wetzlar",
      "telefon": "+49 6441 381190",
      "enlem": "50.58223",
      "boylam": "8.4848",
      "mesafe": "38.6 km"
    },
    {
      "eczaneAdi": "Turm Apotheke",
      "adres": "Hauptstraße 60, 61191 Rosbach v d Höhe",
      "telefon": "+49 6007 7676",
      "enlem": "50.26612",
      "boylam": "8.69888",
      "mesafe": "44.7 km"
    },
    {
      "eczaneAdi": "Markt Apotheke",
      "adres": "Homburger Straße 43, 61184 Karben",
      "telefon": "+49 6039 2506",
      "enlem": "50.2310243",
      "boylam": "8.7707426",
      "mesafe": "45.8 km"
    },
    {
      "eczaneAdi": "Apotheke in Frielendorf",
      "adres": "Hauptstr. 53, 34621 Frielendorf",
      "telefon": "+49 5684 317",
      "enlem": "50.9755861",
      "boylam": "9.3262143",
      "mesafe": "46.0 km"
    },
    {
      "eczaneAdi": "Adler Apotheke",
      "adres": "Obergasse 13, 61250 Usingen",
      "telefon": "+49 6081 66742",
      "enlem": "50.3351",
      "boylam": "8.53689",
      "mesafe": "46.3 km"
    },
    {
      "eczaneAdi": "Engel Apotheke am Buttermarkt",
      "adres": "Karlstr. 4, 36037 Fulda",
      "telefon": "+49 661 928950",
      "enlem": "50.55025",
      "boylam": "9.67722",
      "mesafe": "46.4 km"
    },
    {
      "eczaneAdi": "Bären Apotheke",
      "adres": "Schelde-Lahn-Str. 43, 35239 Steffenberg",
      "telefon": "+49 6464 8056",
      "enlem": "50.8402413",
      "boylam": "8.4715254",
      "mesafe": "47.0 km"
    },
    {
      "eczaneAdi": "Löwen Apotheke",
      "adres": "Innerer Ring 2, 63486 Bruchköbel",
      "telefon": "+49 6181 976597",
      "enlem": "50.1802",
      "boylam": "8.91846",
      "mesafe": "48.2 km"
    },
    {
      "eczaneAdi": "Kurpark Apotheke",
      "adres": "Ludwig-Schmank-Str. 5, 63619 Bad Orb",
      "telefon": "+49 6052 3993",
      "enlem": "50.2244024",
      "boylam": "9.3501042",
      "mesafe": "48.4 km"
    }
  ],
  "Mecklenburg-Vorpommern": [
    {
      "eczaneAdi": "Apotheke am Wasserturm",
      "adres": "Rosenstraße 2, 17166 Teterow",
      "telefon": "+49 3996 1629790",
      "enlem": "53.76898",
      "boylam": "12.579",
      "mesafe": "0.6 km"
    },
    {
      "eczaneAdi": "Apotheke am Distelberg",
      "adres": "Am Eicheneck 6, 18273 Güstrow",
      "telefon": "+49 3843 212068",
      "enlem": "53.809078",
      "boylam": "12.1891445",
      "mesafe": "25.8 km"
    },
    {
      "eczaneAdi": "Löwen-Apotheke",
      "adres": "Neuer Markt 21, 17192 Waren",
      "telefon": "+49 3991 666153",
      "enlem": "53.5145093",
      "boylam": "12.6887047",
      "mesafe": "29.8 km"
    },
    {
      "eczaneAdi": "Pommern-Apotheke",
      "adres": "Adolf-Pompe-Str. 24, 17109 Demmin",
      "telefon": "+49 3998 362366",
      "enlem": "53.90266",
      "boylam": "13.04724",
      "mesafe": "34.2 km"
    },
    {
      "eczaneAdi": "Apotheke im Globus",
      "adres": "Globusring 1, 18184 Roggentin",
      "telefon": "+49 38204 15343",
      "enlem": "54.0753978",
      "boylam": "12.2013015",
      "mesafe": "41.6 km"
    },
    {
      "eczaneAdi": "Bernstein-Apotheke",
      "adres": "H.-Sachs-Allee 12, 18057 Rostock",
      "telefon": "+49 381 4923434",
      "enlem": "54.0894693",
      "boylam": "12.0966982",
      "mesafe": "47.2 km"
    }
  ],
  "Niedersachsen": [
    {
      "eczaneAdi": "Lindenberg Apotheke",
      "adres": "Bahnhofstr. 57, 27305 Bruchhausen-Vilsen",
      "telefon": "+49 4252 3434",
      "enlem": "52.82191",
      "boylam": "8.98631",
      "mesafe": "6.4 km"
    },
    {
      "eczaneAdi": "Geest-Apotheke",
      "adres": "Hauptstr. 46, 27308 Kirchlinteln",
      "telefon": "+49 4236 777",
      "enlem": "52.9415565",
      "boylam": "9.3244272",
      "mesafe": "20.2 km"
    },
    {
      "eczaneAdi": "Uhlen Apotheke",
      "adres": "Rathausstr. 2, 31608 Marklohe",
      "telefon": "+49 5021 15025",
      "enlem": "52.6601345",
      "boylam": "9.1586733",
      "mesafe": "20.8 km"
    },
    {
      "eczaneAdi": "Apotheke am Markt",
      "adres": "Weberweg 2, 28844 Weyhe",
      "telefon": "+49 4203 1300",
      "enlem": "52.98135",
      "boylam": "8.84978",
      "mesafe": "21.9 km"
    },
    {
      "eczaneAdi": "Storchen-Apotheke",
      "adres": "Uphuser Heerstr. 35, 28832 Achim",
      "telefon": "+49 4202 910150",
      "enlem": "53.0273012",
      "boylam": "8.9743033",
      "mesafe": "22.0 km"
    },
    {
      "eczaneAdi": "Schleng-Apotheke",
      "adres": "Schlengstr. 31, 28309 Bremen",
      "telefon": "+49 421 452215",
      "enlem": "53.0508237",
      "boylam": "8.8939178",
      "mesafe": "26.5 km"
    }
  ],
  "Rheinland-Pfalz": [
    {
      "eczaneAdi": "Flora-Apotheke",
      "adres": "Spesenrother Weg 1, 56288 Kastellaun",
      "telefon": "+49 6762 8242",
      "enlem": "50.0711724",
      "boylam": "7.442738",
      "mesafe": "16.2 km"
    },
    {
      "eczaneAdi": "Apo-Mosel OHG Brücken-Apotheke",
      "adres": "Brautrockstr. 45, 56859 Bullay",
      "telefon": "+49 6542 9694659",
      "enlem": "50.04973",
      "boylam": "7.13807",
      "mesafe": "16.4 km"
    },
    {
      "eczaneAdi": "Engel-Apotheke",
      "adres": "Hauptstr. 363, 55743 Idar-Oberstein",
      "telefon": "+49 6781 567298",
      "enlem": "49.70255",
      "boylam": "7.32412",
      "mesafe": "27.9 km"
    },
    {
      "eczaneAdi": "Marien-Apotheke",
      "adres": "Salmstr. 37, 54528 Salmtal",
      "telefon": "+49 6578 989003",
      "enlem": "49.92456",
      "boylam": "6.84094",
      "mesafe": "33.9 km"
    },
    {
      "eczaneAdi": "Ring-Apotheke, Wolfgang Zahn e.K.",
      "adres": "Ringstraße 64a, 55543 Bad Kreuznach",
      "telefon": "+49 671 69968",
      "enlem": "49.8367837",
      "boylam": "7.8637513",
      "mesafe": "41.8 km"
    },
    {
      "eczaneAdi": "Victoria-Apotheke",
      "adres": "Adolfstr. 35, 56112 Lahnstein",
      "telefon": "+49 2621 2226",
      "enlem": "50.302396",
      "boylam": "7.6056425",
      "mesafe": "44.2 km"
    },
    {
      "eczaneAdi": "Apotheke am Römerplatz",
      "adres": "Emser Str. 339, 56076 Koblenz",
      "telefon": "+49 261 9730707",
      "enlem": "50.3287783",
      "boylam": "7.5973001",
      "mesafe": "46.5 km"
    },
    {
      "eczaneAdi": "Apotheke am Rosengarten",
      "adres": "Bahnhofstr. 48, 66869 Kusel",
      "telefon": "+49 6381 7921",
      "enlem": "49.5377305",
      "boylam": "7.4060946",
      "mesafe": "46.7 km"
    }
  ],
  "Saarland": [
    {
      "eczaneAdi": "Marien-Apotheke",
      "adres": "Kirchplatz 2, 66571 Eppelborn",
      "telefon": "06881/7128",
      "enlem": "49.405948",
      "boylam": "6.9664913",
      "mesafe": "2.6 km"
    },
    {
      "eczaneAdi": "Berg- und Hütten-Apotheke OHG",
      "adres": "Saarbrücker Str. 58, 66299 Friedrichsthal",
      "telefon": "06897/8215",
      "enlem": "49.3215396",
      "boylam": "7.0946256",
      "mesafe": "12.4 km"
    },
    {
      "eczaneAdi": "Glückauf-Apotheke",
      "adres": "Saarbrücker Str. 267, 66125 Saarbrücken-Dudweiler",
      "telefon": "06897/77075",
      "enlem": "49.2773447",
      "boylam": "7.0362306",
      "mesafe": "13.3 km"
    },
    {
      "eczaneAdi": "St. Josef-Apotheke",
      "adres": "Dillinger Straße 59, 66763 Dillingen-Diefflen",
      "telefon": "06831/9663639",
      "enlem": "49.3714809",
      "boylam": "6.7604526",
      "mesafe": "14.1 km"
    },
    {
      "eczaneAdi": "Marien-Apotheke",
      "adres": "Kirchstraße 9, 66359 Bous",
      "telefon": "06834/2300",
      "enlem": "49.2756306",
      "boylam": "6.7968808",
      "mesafe": "16.6 km"
    },
    {
      "eczaneAdi": "Apotheke am kleinen Markt",
      "adres": "An der Kirche 1, 66687 Wadern",
      "telefon": "06871/9013-0",
      "enlem": "49.5389",
      "boylam": "6.88978",
      "mesafe": "17.8 km"
    },
    {
      "eczaneAdi": "Engel-Apotheke",
      "adres": "Talstraße 128, 66701 Beckingen",
      "telefon": "06835/2435",
      "enlem": "49.394082",
      "boylam": "6.7007654",
      "mesafe": "18.4 km"
    },
    {
      "eczaneAdi": "Rats-Apotheke",
      "adres": "Marktplatz 10a, 66386 St. Ingbert-Hassel",
      "telefon": "06894/956028",
      "enlem": "49.2646766",
      "boylam": "7.1634216",
      "mesafe": "20.2 km"
    },
    {
      "eczaneAdi": "Furpach-Apotheke",
      "adres": "Ludwigsthaler Str. 9, 66539 Neunkirchen",
      "telefon": "06821/31859",
      "enlem": "49.3234271",
      "boylam": "7.2186961",
      "mesafe": "20.4 km"
    },
    {
      "eczaneAdi": "Einhorn-Apotheke",
      "adres": "Saargemünder Str. 165, 66130 Saarbrücken-Güdingen",
      "telefon": "0681/872157",
      "enlem": "49.2003937",
      "boylam": "7.0281963",
      "mesafe": "21.1 km"
    },
    {
      "eczaneAdi": "Margarethen-Apotheke",
      "adres": "Kuseler Str. 31, 66606 St. Wendel-Niederkirchen",
      "telefon": "06856/780",
      "enlem": "49.4686937",
      "boylam": "7.2526177",
      "mesafe": "23.6 km"
    }
  ],
  "Sachsen": [
    {
      "eczaneAdi": "Berg-Apotheke",
      "adres": "Markt 8, 09618 Brand-Erbisdorf",
      "telefon": "+49 37322 2227",
      "enlem": "50.86966",
      "boylam": "13.32263",
      "mesafe": "11.7 km"
    },
    {
      "eczaneAdi": "Berg-Apotheke",
      "adres": "Hauptstraße 18, 01728 Bannewitz / OT Possendorf",
      "telefon": "+49 35206 21306",
      "enlem": "50.9661645",
      "boylam": "13.7123685",
      "mesafe": "18.3 km"
    },
    {
      "eczaneAdi": "easyApotheke Löbtau",
      "adres": "Kesselsdorfer Straße 8, 01159 Dresden",
      "telefon": "+49 351 21293633",
      "enlem": "51.04384",
      "boylam": "13.70325",
      "mesafe": "21.4 km"
    },
    {
      "eczaneAdi": "Neue Apotheke Altstrehlen",
      "adres": "Altstrehlen 3, 01219 Dresden",
      "telefon": "+49 351 4708120",
      "enlem": "51.02808",
      "boylam": "13.76206",
      "mesafe": "24.0 km"
    },
    {
      "eczaneAdi": "Spitzgrund-Apotheke",
      "adres": "Moritzburger Str. 74, 01640 Coswig",
      "telefon": "+49 3523 62762",
      "enlem": "51.13811",
      "boylam": "13.59041",
      "mesafe": "25.0 km"
    }
  ],
  "Sachsen-Anhalt": [
    {
      "eczaneAdi": "Die Herz Apotheke Reform",
      "adres": "Kosmos-Promenade 6, 39118 Magdeburg",
      "telefon": "+49 391 611610",
      "enlem": "52.0895003",
      "boylam": "11.6126669",
      "mesafe": "10.8 km"
    },
    {
      "eczaneAdi": "Dr. Löwe-Apotheke",
      "adres": "Magdeburger Str. 105, 39240 Calbe/Saale",
      "telefon": "+49 39291 2860",
      "enlem": "51.9055525",
      "boylam": "11.7717242",
      "mesafe": "12.5 km"
    },
    {
      "eczaneAdi": "St. Georg-Apotheke",
      "adres": "Beimsplatz 6, 39110 Magdeburg",
      "telefon": "+49 391 7391087",
      "enlem": "52.12837",
      "boylam": "11.59531",
      "mesafe": "15.1 km"
    },
    {
      "eczaneAdi": "Saale-Apotheke",
      "adres": "Franz-Hallström-Str. 6, 06429 Nienburg",
      "telefon": "+49 34721 30870",
      "enlem": "51.8362909",
      "boylam": "11.7689568",
      "mesafe": "19.8 km"
    },
    {
      "eczaneAdi": "Neue Apotheke",
      "adres": "Dessauer Straße 41/43, 39261 Zerbst/Anhalt",
      "telefon": "+49 3923 3406",
      "enlem": "51.9602644",
      "boylam": "12.0921785",
      "mesafe": "27.5 km"
    }
  ],
  "Schleswig-Holstein": [
    {
      "eczaneAdi": "Stadt Apotheke",
      "adres": "Bahnhofstr. 2, 24589 Nortorf",
      "telefon": "+49 4392 3686",
      "enlem": "54.16786",
      "boylam": "9.85446",
      "mesafe": "2.9 km"
    },
    {
      "eczaneAdi": "Ring-Apotheke bei Meyer`s",
      "adres": "Goethestr. 13, 24534 Neumünster",
      "telefon": "04321-5582831",
      "enlem": "54.0808016",
      "boylam": "9.9955296",
      "mesafe": "16.3 km"
    },
    {
      "eczaneAdi": "Garnison-Apotheke",
      "adres": "Paradeplatz 8, 24768 Rendsburg",
      "telefon": "04331-22454",
      "enlem": "54.2995294",
      "boylam": "9.6643971",
      "mesafe": "16.3 km"
    },
    {
      "eczaneAdi": "Apotheke Hohn",
      "adres": "Hauptstr. 14, 24806 Hohn",
      "telefon": "+49 4335 92700",
      "enlem": "54.30159",
      "boylam": "9.51109",
      "mesafe": "24.0 km"
    },
    {
      "eczaneAdi": "FISCHERS Apotheke  Wittensee",
      "adres": "Im Wiesengrund 2, 24361 Groß Wittensee",
      "telefon": "04356-677",
      "enlem": "54.4028475",
      "boylam": "9.7681418",
      "mesafe": "24.5 km"
    },
    {
      "eczaneAdi": "Adler Apotheke",
      "adres": "Jungfernstieg 37, 24116 Kiel",
      "telefon": "+49 431 91785",
      "enlem": "54.32483",
      "boylam": "10.12174",
      "mesafe": "24.9 km"
    },
    {
      "eczaneAdi": "Ring-Apotheke",
      "adres": "Elisabethstr. 49, 24143 Kiel",
      "telefon": "0431-731803",
      "enlem": "54.3127317",
      "boylam": "10.1473399",
      "mesafe": "25.5 km"
    },
    {
      "eczaneAdi": "VITAL-Apotheke",
      "adres": "Eckernförder Str. 362, 24107 Kiel",
      "telefon": "0431-220020",
      "enlem": "54.3528827",
      "boylam": "10.0903301",
      "mesafe": "25.6 km"
    },
    {
      "eczaneAdi": "Apotheke am Markt",
      "adres": "Kirchhofsallee 2, 24214 Gettorf",
      "telefon": "04346-412576",
      "enlem": "54.4076397",
      "boylam": "9.9744999",
      "mesafe": "26.7 km"
    }
  ],
  "Thüringen": [
    {
      "eczaneAdi": "EGA-Apotheke",
      "adres": "Gothaer Straße 22, 99094 Erfurt",
      "telefon": "+49 361 7893490",
      "enlem": "50.9610823",
      "boylam": "10.9857271",
      "mesafe": "7.6 km"
    },
    {
      "eczaneAdi": "Germania-Apotheke",
      "adres": "Thälmannstraße 25, 99085 Erfurt",
      "telefon": "+49 361 5623214",
      "enlem": "50.97917",
      "boylam": "11.04247",
      "mesafe": "8.6 km"
    },
    {
      "eczaneAdi": "Apotheke Neudietendorf",
      "adres": "Kirchstr. 15, 99192 Neudietendorf",
      "telefon": "+49 36202 90308",
      "enlem": "50.9125362",
      "boylam": "10.9126485",
      "mesafe": "8.9 km"
    },
    {
      "eczaneAdi": "Apotheke am Goetheplatz",
      "adres": "Goetheplatz 6, 99423 Weimar",
      "telefon": "+49 3643 811800",
      "enlem": "50.981808",
      "boylam": "11.3250323",
      "mesafe": "22.1 km"
    },
    {
      "eczaneAdi": "Antonius-Apotheke",
      "adres": "Hohe Straße 2a, 98693 Ilmenau, OT Unterpörlitz",
      "telefon": "+49 3677 63435",
      "enlem": "50.6994714",
      "boylam": "10.9281279",
      "mesafe": "23.8 km"
    },
    {
      "eczaneAdi": "Schmetterling-Apotheke im Kaufland Gotha",
      "adres": "Bürgeraue 2, 99867 Gotha",
      "telefon": "+49 3621 5045250",
      "enlem": "50.9485766",
      "boylam": "10.6956922",
      "mesafe": "24.6 km"
    }
  ]
}